SunnyNet/CertManager.py
SunnyNet/Event.py
SunnyNet/HTTPClient.py
SunnyNet/Queue.py
SunnyNet/SunnyDLL.py
SunnyNet/SunnyNet.py
SunnyNet/SunnyNet64.dll
SunnyNet/TCPTools.py
SunnyNet/UDPTools.py
SunnyNet/WebsocketTools.py
SunnyNet/__init__.py
SunnyNet/cli.py
SunnyNet/download_libs.py
SunnyNet/library_urls.py
SunnyNet/tools.py
sunnynet-1.5.18.dist-info/licenses/LICENSE
sunnynet-1.5.18.dist-info/METADATA
sunnynet-1.5.18.dist-info/WHEEL
sunnynet-1.5.18.dist-info/entry_points.txt
sunnynet-1.5.18.dist-info/top_level.txt
sunnynet-1.5.18.dist-info/RECORD
