Metadata-Version: 2.4
Name: SunnyNet
Version: 1.5.18
Summary: SunnyNet网络中间件 - 强大的网络代理和抓包工具
Home-page: https://github.com/yourusername/SunnyNet
Author: 秦天
Author-email: 
License-Expression: MIT
Project-URL: Homepage, https://github.com/yourusername/SunnyNet
Project-URL: Bug Reports, https://github.com/yourusername/SunnyNet/issues
Project-URL: Source, https://github.com/yourusername/SunnyNet
Keywords: network,proxy,middleware,http,tcp,udp,websocket
Classifier: Programming Language :: Python :: 3
Classifier: Programming Language :: Python :: 3.7
Classifier: Programming Language :: Python :: 3.8
Classifier: Programming Language :: Python :: 3.9
Classifier: Programming Language :: Python :: 3.10
Classifier: Programming Language :: Python :: 3.11
Classifier: Programming Language :: Python :: 3.12
Classifier: Operating System :: Microsoft :: Windows
Classifier: Operating System :: POSIX :: Linux
Classifier: Development Status :: 4 - Beta
Classifier: Intended Audience :: Developers
Classifier: Topic :: Internet :: Proxy Servers
Classifier: Topic :: Software Development :: Libraries :: Python Modules
Requires-Python: >=3.7
License-File: LICENSE
Dynamic: home-page
Dynamic: license-file
Dynamic: requires-python
